{
	"textures": {
		"0": "animated_java:blueprint/troll/troll",
		"particle": "minecraft:item/pufferfish"
	},
	"display": {
		"head": {
			"rotation": [0, 180, 0]
		}
	},
	"elements": [
		{
			"from": [10.49607, 3.16594, 5.83824],
			"to": [22.25351, 6.89354, 5.83824],
			"rotation": {
				"angle": 22.5,
				"axis": "y",
				"origin": [15.29517, 5.20734, 5.76478]
			},
			"faces": {
				"north": {
					"uv": [0, 8.84375, 1.25, 9.21875],
					"texture": "#0"
				},
				"east": {
					"uv": [0, 0, 0, 0.375],
					"texture": "#0"
				},
				"south": {
					"uv": [1.25, 8.84375, 0, 9.21875],
					"texture": "#0"
				},
				"west": {
					"uv": [0, 0, 0, 0.375],
					"texture": "#0"
				},
				"up": {
					"uv": [0.375, 0, 0, 0],
					"texture": "#0"
				},
				"down": {
					"uv": [0.375, 0, 0, 0],
					"texture": "#0"
				}
			}
		},
		{
			"from": [-1.74649, 3.16594, 5.83824],
			"to": [10.01094, 6.89354, 5.83824],
			"rotation": {
				"angle": -22.5,
				"axis": "y",
				"origin": [5.21185, 5.20734, 5.76478]
			},
			"faces": {
				"north": {
					"uv": [1.25, 8.84375, 0, 9.21875],
					"texture": "#0"
				},
				"east": {
					"uv": [0, 0, 0, 0.375],
					"texture": "#0"
				},
				"south": {
					"uv": [0, 8.84375, 1.25, 9.21875],
					"texture": "#0"
				},
				"west": {
					"uv": [0, 0, 0, 0.375],
					"texture": "#0"
				},
				"up": {
					"uv": [0, 0, 0.375, 0],
					"texture": "#0"
				},
				"down": {
					"uv": [0, 0, 0.375, 0],
					"texture": "#0"
				}
			}
		},
		{
			"from": [8.48989, 6.04043, 3.49298],
			"to": [11.42925, 8.39191, 8.97979],
			"rotation": {
				"angle": -22.5,
				"axis": "x",
				"origin": [9.95957, 7.21617, 6.43234]
			},
			"faces": {
				"north": {
					"uv": [0.84375, 6.5, 1.09375, 6.6875],
					"texture": "#0"
				},
				"east": {
					"uv": [5.5, 2, 5.9375, 2.1875],
					"texture": "#0"
				},
				"south": {
					"uv": [6.6875, 3.0625, 6.90625, 3.25],
					"texture": "#0"
				},
				"west": {
					"uv": [5.9375, 2, 6.375, 2.1875],
					"texture": "#0"
				},
				"up": {
					"uv": [1.4375, 5.84375, 1.21875, 5.40625],
					"texture": "#0"
				},
				"down": {
					"uv": [1.4375, 5.84375, 1.21875, 6.28125],
					"texture": "#0"
				}
			}
		},
		{
			"from": [10.84138, 5.45256, 7.02021],
			"to": [13.19287, 7.41213, 8.97979],
			"rotation": {
				"angle": -22.5,
				"axis": "y",
				"origin": [12.50702, 7.21617, 6.43234]
			},
			"faces": {
				"north": {
					"uv": [6.28125, 5.65625, 6.46875, 5.8125],
					"texture": "#0"
				},
				"east": {
					"uv": [7.1875, 5.0625, 7.34375, 5.21875],
					"texture": "#0"
				},
				"south": {
					"uv": [6.28125, 5.8125, 6.46875, 5.96875],
					"texture": "#0"
				},
				"west": {
					"uv": [7.3125, 4.125, 7.46875, 4.28125],
					"texture": "#0"
				},
				"up": {
					"uv": [2.15625, 6.875, 1.96875, 6.71875],
					"texture": "#0"
				},
				"down": {
					"uv": [2.34375, 6.71875, 2.15625, 6.875],
					"texture": "#0"
				}
			}
		},
		{
			"from": [6.77103, 5.45256, 6.79525],
			"to": [9.12251, 7.41213, 8.75482],
			"rotation": {
				"angle": 22.5,
				"axis": "y",
				"origin": [8, 7.21617, 6.43234]
			},
			"faces": {
				"north": {
					"uv": [6.46875, 5.65625, 6.28125, 5.8125],
					"texture": "#0"
				},
				"east": {
					"uv": [7.46875, 4.125, 7.3125, 4.28125],
					"texture": "#0"
				},
				"south": {
					"uv": [6.46875, 5.8125, 6.28125, 5.96875],
					"texture": "#0"
				},
				"west": {
					"uv": [7.34375, 5.0625, 7.1875, 5.21875],
					"texture": "#0"
				},
				"up": {
					"uv": [1.96875, 6.875, 2.15625, 6.71875],
					"texture": "#0"
				},
				"down": {
					"uv": [2.15625, 6.71875, 2.34375, 6.875],
					"texture": "#0"
				}
			}
		}
	]
}